.DS_Store
.hgignore
.hgtags
CaChannel.py
EPICS_config_Darwin.py
EPICS_config_Darwin.pyc
EPICS_config_Linux.py
EPICS_config_Win32.py
EPICS_config_common.py
EPICS_config_local_sample.py
MANIFEST
MANIFEST.in
Makefile
Numeric.py
PKG-INFO
README
README.html
README.md
README.rst
_ca.c
_ca314.cpp
_ca_fnal.py
_ca_kek.py
_conv_helper.cpp
ca.py
caError.py
cadefs.py
caerr.py
caerr_wrap.c
calib.pxd
calib.pyx
calib3.cpp
db_access.pxd
epicsVersion.py
foo.py
gen_caerrpy.c
generate_caError.py
hgstamp.py
makeEpicsVersion.py
printfn.py
setup.cfg
setup.py
PythonCA.egg-info/PKG-INFO
PythonCA.egg-info/SOURCES.txt
PythonCA.egg-info/dependency_links.txt
PythonCA.egg-info/top_level.txt
cas/__init__.py
cas/caq.py
cas/cas.py
cas/xca.py
doc/InstallationMemo.html
doc/InstallationMemo.md
doc/InstallationMemo.rst
doc/InstallationMemo.rst~
doc/sphinx/Makefile
doc/sphinx/build/html/InstallationMemo.html
doc/sphinx/build/html/ReleaseMemo-1.23.2.2.1.html
doc/sphinx/build/html/genindex.html
doc/sphinx/build/html/index.html
doc/sphinx/build/html/search.html
doc/sphinx/build/html/_sources/InstallationMemo.rst.txt
doc/sphinx/build/html/_sources/ReleaseMemo-1.23.2.2.1.rst.txt
doc/sphinx/build/html/_sources/index.rst.txt
doc/sphinx/build/latex/Makefile
doc/sphinx/build/latex/PythonCAPythonmoduleforEPICSCAlibrary.tex
doc/sphinx/source/InstallationMemo.rst
doc/sphinx/source/Makefile
doc/sphinx/source/ReleaseMemo-1.23.2.2.1.rst
doc/sphinx/source/conf.py
doc/sphinx/source/index.rst
sample/CaSimple.py
sample/CaSimple_usingQueue.py
sample/DummySimple.py
sample/QtSample1.py
sample/SyncGroupSample.py
sample/TkMinimal.py
sample/TkMinimal.tcl
sample/TkRandom.py
sample/TkRandom2.py
sample/TkSample1.1.py
sample/TkSample1.py
sample/TkSample2.py
sample/TkSample3.py
sample/TkSimple2.py
sample/TkTest.py
sample/WxMinimal.py
sample/WxRandom.py
sample/WxSample1.py
sample/WxSample2.py
sample/WxSimple.py
sample/WxSimple2.py
sample/__init__.py
sample/caAlarmSeverity.py
sample/caBadSample2.py
sample/caBadSample3.py
sample/caBadSampleChannels.py
sample/caBadSampleThreadLock.py
sample/epicsQt.py
sample/ex_tk4.py
sample/ex_tk4n.py
sample/ezca.py
