Metadata-Version: 2.1
Name: PythonCA
Version: 1.23.3.12
Summary: EPICS CA library interface module
Home-page: http://www-acc.kek.jp/EPICS_Gr/products.html
Download-URL: https://pypi.org/project/PythonCA/
Author: Noboru Yamamoto, KEK, JAPAN
Author-email: Noboru.YAMAMOTO@kek.jp
Classifier: Programming Language :: C++
Classifier: Programming Language :: Python :: 2.7
Classifier: Programming Language :: Python :: 3.6
Classifier: Topic :: Scientific/Engineering :: Interface Engine/Protocol Translator
